__init__.py
varboxes.py
varboxes-1.1.dist-info/licenses/LICENSE
varboxes-1.1.dist-info/METADATA
varboxes-1.1.dist-info/WHEEL
varboxes-1.1.dist-info/top_level.txt
varboxes-1.1.dist-info/RECORD
