Metadata-Version: 2.4
Name: varboxes
Version: 1.1
Summary: a varbox allows to store parmanently python variables between sessions
Author: Imam Usmani
Project-URL: Source Code, https://github.com/ImamAzim/varboxes
Project-URL: Documentation, https://varboxes.readthedocs.io/en/latest/index.html
Classifier: Intended Audience :: Developers
Classifier: License :: OSI Approved :: GNU General Public License v3 (GPLv3)
Classifier: Natural Language :: English
Classifier: Programming Language :: Python :: 3
Classifier: Operating System :: POSIX :: Linux
Requires-Python: >=3.7
License-File: LICENSE
Requires-Dist: xdg
Provides-Extra: dev
Requires-Dist: pytest; extra == "dev"
Requires-Dist: flake8; extra == "dev"
Requires-Dist: ipython; extra == "dev"
Requires-Dist: sphinx; extra == "dev"
Requires-Dist: build; extra == "dev"
Requires-Dist: twine; extra == "dev"
Requires-Dist: sphinx-rtd-theme; extra == "dev"
Dynamic: license-file
